{
  "2006.0": {
    "NA": [41.49, "Wii Sports"],
    "EU": [29.02, "Wii Sports"],
    "JP": [6.5, "New Super Mario Bros."],
    "OT": [8.46, "Wii Sports"]
  },
  "1985.0": {
    "NA": [29.08, "Super Mario Bros."],
    "EU": [3.58, "Super Mario Bros."],
    "JP": [6.81, "Super Mario Bros."],
    "OT": [0.77, "Super Mario Bros."]
  },
  "2008.0": {
    "NA": [15.85, "Mario Kart Wii"],
    "EU": [12.88, "Mario Kart Wii"],
    "JP": [4.13, "Monster Hunter Freedom Unite"],
    "OT": [3.31, "Mario Kart Wii"]
  },
  "2009.0": {
    "NA": [15.75, "Wii Sports Resort"],
    "EU": [11.01, "Wii Sports Resort"],
    "JP": [4.7, "New Super Mario Bros. Wii"],
    "OT": [2.96, "Wii Sports Resort"]
  },
  "1996.0": {
    "NA": [11.27, "Pokemon Red/Pokemon Blue"],
    "EU": [8.89, "Pokemon Red/Pokemon Blue"],
    "JP": [10.22, "Pokemon Red/Pokemon Blue"],
    "OT": [1.0, "Pokemon Red/Pokemon Blue"]
  },
  "1989.0": {
    "NA": [23.2, "Tetris"],
    "EU": [2.71, "Super Mario Land"],
    "JP": [4.22, "Tetris"],
    "OT": [0.58, "Tetris"]
  },
  "1984.0": {
    "NA": [26.93, "Duck Hunt"],
    "EU": [0.63, "Duck Hunt"],
    "JP": [2.46, "Golf"],
    "OT": [0.47, "Duck Hunt"]
  },
  "2005.0": {
    "NA": [9.81, "Mario Kart DS"],
    "EU": [11.0, "Nintendogs"],
    "JP": [5.33, "Animal Crossing: Wild World"],
    "OT": [2.75, "Nintendogs"]
  },
  "1999.0": {
    "NA": [9.0, "Pokemon Gold/Pokemon Silver"],
    "EU": [6.18, "Pokemon Gold/Pokemon Silver"],
    "JP": [7.2, "Pokemon Gold/Pokemon Silver"],
    "OT": [0.71, "Pokemon Gold/Pokemon Silver"]
  },
  "2007.0": {
    "NA": [8.94, "Wii Fit"],
    "EU": [8.03, "Wii Fit"],
    "JP": [3.6, "Wii Fit"],
    "OT": [2.93, "Pro Evolution Soccer 2008"]
  },
  "2010.0": {
    "NA": [14.97, "Kinect Adventures!"],
    "EU": [4.94, "Kinect Adventures!"],
    "JP": [5.65, "Pokemon Black/Pokemon White"],
    "OT": [2.12, "Gran Turismo 5"]
  },
  "2013.0": {
    "NA": [9.63, "Grand Theft Auto V"],
    "EU": [9.27, "Grand Theft Auto V"],
    "JP": [4.34, "Pokemon X/Pokemon Y"],
    "OT": [4.14, "Grand Theft Auto V"]
  },
  "2004.0": {
    "NA": [9.43, "Grand Theft Auto: San Andreas"],
    "EU": [6.21, "World of Warcraft"],
    "JP": [3.61, "Dragon Quest VIII: Journey of the Cursed King"],
    "OT": [10.57, "Grand Theft Auto: San Andreas"]
  },
  "1990.0": {
    "NA": [12.78, "Super Mario World"],
    "EU": [3.75, "Super Mario World"],
    "JP": [3.54, "Super Mario World"],
    "OT": [0.55, "Super Mario World"]
  },
  "1988.0": {
    "NA": [9.54, "Super Mario Bros. 3"],
    "EU": [3.44, "Super Mario Bros. 3"],
    "JP": [3.84, "Super Mario Bros. 3"],
    "OT": [0.46, "Super Mario Bros. 3"]
  },
  "2002.0": {
    "NA": [8.41, "Grand Theft Auto: Vice City"],
    "EU": [5.49, "Grand Theft Auto: Vice City"],
    "JP": [5.38, "Pokemon Ruby/Pokemon Sapphire"],
    "OT": [1.78, "Grand Theft Auto: Vice City"]
  },
  "2001.0": {
    "NA": [6.99, "Grand Theft Auto III"],
    "EU": [5.09, "Gran Turismo 3: A-Spec"],
    "JP": [2.73, "Final Fantasy X"],
    "OT": [1.3, "Grand Theft Auto III"]
  },
  "2011.0": {
    "NA": [9.03, "Call of Duty: Modern Warfare 3"],
    "EU": [5.82, "Call of Duty: Modern Warfare 3"],
    "JP": [2.67, "Mario Kart 7"],
    "OT": [1.62, "Call of Duty: Modern Warfare 3"]
  },
  "1998.0": {
    "NA": [5.89, "Pokémon Yellow: Special Pikachu Edition"],
    "EU": [5.04, "Pokémon Yellow: Special Pikachu Edition"],
    "JP": [3.12, "Pokémon Yellow: Special Pikachu Edition"],
    "OT": [0.59, "Pokémon Yellow: Special Pikachu Edition"]
  },
  "2015.0": {
    "NA": [5.77, "Call of Duty: Black Ops 3"],
    "EU": [6.06, "FIFA 16"],
    "JP": [2.78, "Monster Hunter X"],
    "OT": [2.31, "Call of Duty: Black Ops 3"]
  },
  "2012.0": {
    "NA": [8.25, "Call of Duty: Black Ops II"],
    "EU": [5.88, "Call of Duty: Black Ops II"],
    "JP": [4.36, "Animal Crossing: New Leaf"],
    "OT": [2.52, "Call of Duty: Black Ops II"]
  },
  "2014.0": {
    "NA": [4.23, "Pokemon Omega Ruby/Pokemon Alpha Sapphire"],
    "EU": [5.81, "Grand Theft Auto V"],
    "JP": [3.18, "Yokai Watch 2 Ganso/Honke"],
    "OT": [2.02, "Grand Theft Auto V"]
  },
  "1992.0": {
    "NA": [6.16, "Super Mario Land 2: 6 Golden Coins"],
    "EU": [2.04, "Super Mario Land 2: 6 Golden Coins"],
    "JP": [3.81, "Super Mario Kart"],
    "OT": [0.29, "Super Mario Land 2: 6 Golden Coins"]
  },
  "1997.0": {
    "NA": [5.8, "GoldenEye 007"],
    "EU": [3.87, "Gran Turismo"],
    "JP": [3.28, "Final Fantasy VII"],
    "OT": [0.96, "Final Fantasy VII"]
  },
  "1993.0": {
    "NA": [5.99, "Super Mario All-Stars"],
    "EU": [2.15, "Super Mario All-Stars"],
    "JP": [2.12, "Super Mario All-Stars"],
    "OT": [0.29, "Super Mario All-Stars"]
  },
  "1994.0": {
    "NA": [4.36, "Donkey Kong Country"],
    "EU": [2.79, "Myst"],
    "JP": [3.0, "Donkey Kong Country"],
    "OT": [0.34, "Donkey Kong"]
  },
  "1982.0": {
    "NA": [7.28, "Pac-Man"],
    "EU": [0.45, "Pac-Man"],
    "JP": [0, "-"],
    "OT": [0.08, "Pac-Man"]
  },
  "2003.0": {
    "NA": [4.12, "Mario Kart: Double Dash!!"],
    "EU": [2.83, "Need for Speed Underground"],
    "JP": [2.11, "Final Fantasy X-2"],
    "OT": [1.02, "Need for Speed Underground"]
  },
  "1986.0": {
    "NA": [3.74, "The Legend of Zelda"],
    "EU": [0.93, "The Legend of Zelda"],
    "JP": [2.65, "Super Mario Bros.: The Lost Levels"],
    "OT": [1.51, "Dragon Warrior"]
  },
  "2000.0": {
    "NA": [3.05, "Tony Hawk's Pro Skater 2"],
    "EU": [2.1, "Driver 2"],
    "JP": [4.1, "Dragon Quest VII: Warriors of Eden"],
    "OT": [0.99, "Pokémon Crystal Version"]
  },
  "1995.0": {
    "NA": [2.26, "Killer Instinct"],
    "EU": [2.27, "Warcraft II: Tides of Darkness"],
    "JP": [3.19, "Dragon Quest VI: Maboroshi no Daichi"],
    "OT": [0.23, "Warcraft II: Tides of Darkness"]
  },
  "2016.0": {
    "NA": [1.3, "Uncharted 4: A Thief's End"],
    "EU": [3.75, "FIFA 17"],
    "JP": [1.27, "Yokai Watch 3"],
    "OT": [0.69, "FIFA 17"]
  },
  "1991.0": {
    "NA": [3.03, "Sonic the Hedgehog"],
    "EU": [0.91, "The Legend of Zelda: A Link to the Past"],
    "JP": [1.33, "Final Fantasy II"],
    "OT": [0.13, "The Legend of Zelda: A Link to the Past"]
  },
  "1981.0": {
    "NA": [4.21, "Pitfall!"],
    "EU": [0.24, "Pitfall!"],
    "JP": [0, "-"],
    "OT": [0.05, "Pitfall!"]
  },
  "1987.0": {
    "NA": [2.19, "Zelda II: The Adventure of Link"],
    "EU": [0.5, "Zelda II: The Adventure of Link"],
    "JP": [2.41, "Dragon Warrior II"],
    "OT": [0.08, "Zelda II: The Adventure of Link"]
  },
  "1980.0": {
    "NA": [4.0, "Asteroids"],
    "EU": [0.26, "Asteroids"],
    "JP": [0, "-"],
    "OT": [0.05, "Asteroids"]
  },
  "1983.0": {
    "NA": [1.22, "Pitfall II: Lost Caverns"],
    "EU": [0.12, "Mario Bros."],
    "JP": [2.35, "Baseball"],
    "OT": [0.02, "Baseball"]
  },
  "1978.0": {
    "NA": [2.36, "Space Invaders"],
    "EU": [0.14, "Space Invaders"],
    "JP": [0, "-"],
    "OT": [0.03, "Space Invaders"]
  },
  "1977.0": {
    "NA": [1.17, "Combat"],
    "EU": [0.07, "Combat"],
    "JP": [0, "-"],
    "OT": [0.01, "Combat"]
  },
  "2020.0": {
    "NA": [0.27, "Imagine: Makeup Artist"],
    "EU": [0, "-"],
    "JP": [0, "-"],
    "OT": [0.02, "Imagine: Makeup Artist"]
  },
  "2017.0": {
    "NA": [0, "-"],
    "EU": [0, "-"],
    "JP": [0.03, "Phantasy Star Online 2 Episode 4: Deluxe Package"],
    "OT": [0, "-"]
  }
}
